user_vpetrov/__init__.py
user_vpetrov/config.py
user_vpetrov/crud.py
user_vpetrov/database.py
user_vpetrov/models.py
user_vpetrov/schemas.py
user_vpetrov/validators.py
user_vpetrov-0.2.5.dist-info/METADATA
user_vpetrov-0.2.5.dist-info/WHEEL
user_vpetrov-0.2.5.dist-info/top_level.txt
user_vpetrov-0.2.5.dist-info/RECORD
